Metadata-Version: 2.1
Name: vdk-logging-json
Version: 0.1.418423702
Summary: Versatile Data Kit SDK plugin that changes logging output to JSON format.
Home-page: https://github.com/vmware/versatile-data-kit
License: UNKNOWN
Platform: UNKNOWN
Classifier: Development Status :: 4 - Beta
Classifier: License :: OSI Approved :: Apache Software License
Classifier: Programming Language :: Python :: 3.7
Classifier: Programming Language :: Python :: 3.8
Classifier: Programming Language :: Python :: 3.9
Classifier: Programming Language :: Python :: 3.10
